abstract_webtools/__init__.py
abstract_webtools/imports/__init__.py
abstract_webtools/imports/src/__init__.py
abstract_webtools/imports/src/functions/DomainManager.py
abstract_webtools/imports/src/functions/__init__.py
abstract_webtools/imports/src/functions/imports.py
abstract_webtools/imports/src/functions/specUrl_utils.py
abstract_webtools/imports/src/functions/url_utils.py
abstract_webtools/imports/src/functions/utils.py
abstract_webtools/imports/src/functions/domain_utils/__init__.py
abstract_webtools/imports/src/functions/domain_utils/correct_url_utils.py
abstract_webtools/imports/src/functions/domain_utils/domain_parse_utils.py
abstract_webtools/imports/src/functions/domain_utils/get_strip_utils.py
abstract_webtools/imports/src/functions/providers/__init__.py
abstract_webtools/imports/src/functions/providers/main.py
abstract_webtools/imports/src/functions/providers/src/__init__.py
abstract_webtools/imports/src/functions/providers/src/direct_file.py
abstract_webtools/imports/src/functions/providers/src/facebook.py
abstract_webtools/imports/src/functions/providers/src/giphy.py
abstract_webtools/imports/src/functions/providers/src/imgur.py
abstract_webtools/imports/src/functions/providers/src/instagram.py
abstract_webtools/imports/src/functions/providers/src/pinterest.py
abstract_webtools/imports/src/functions/providers/src/reddit.py
abstract_webtools/imports/src/functions/providers/src/tenor.py
abstract_webtools/imports/src/functions/providers/src/tiktok.py
abstract_webtools/imports/src/functions/providers/src/twitch.py
abstract_webtools/imports/src/functions/providers/src/twitter.py
abstract_webtools/imports/src/functions/providers/src/vimeo.py
abstract_webtools/imports/src/functions/providers/src/youtube.py
abstract_webtools/imports/src/functions/titles/__init__.py
abstract_webtools/imports/src/functions/titles/title_variants.py
abstract_webtools/imports/src/functions/titles/titles.py
abstract_webtools/imports/src/imports/__init__.py
abstract_webtools-0.1.6.383.dist-info/METADATA
abstract_webtools-0.1.6.383.dist-info/WHEEL
abstract_webtools-0.1.6.383.dist-info/top_level.txt
abstract_webtools-0.1.6.383.dist-info/RECORD
