Metadata-Version: 2.4
Name: abstract_webtools
Version: 0.1.6.383
Summary: Utilities for fetching/parsing web content with requests/urllib3/BS4 and helpers.
Home-page: https://github.com/AbstractEndeavors/abstract_webtools
Author: putkoff
Author-email: partners@abstractendeavors.com
Classifier: Development Status :: 3 - Alpha
Classifier: Intended Audience :: Developers
Classifier: License :: OSI Approved :: MIT License
Classifier: Programming Language :: Python :: 3
Classifier: Programming Language :: Python :: 3.11
Requires-Python: >=3.8
Requires-Dist: requests>=2.31.0
Requires-Dist: urllib3>=2.0.4
Requires-Dist: beautifulsoup4>=4.12.0
Provides-Extra: gui
Requires-Dist: PySimpleGUI>=4.60.5; extra == "gui"
Requires-Dist: PyQt5>=5.15.0; extra == "gui"
Provides-Extra: drivers
Requires-Dist: selenium>=4.15.2; extra == "drivers"
Requires-Dist: webdriver-manager>=4.0.0; extra == "drivers"
Provides-Extra: media
Requires-Dist: yt-dlp>=2024.4.9; extra == "media"
Requires-Dist: m3u8>=4.0.0; extra == "media"
Dynamic: author
Dynamic: author-email
Dynamic: classifier
Dynamic: description
Dynamic: description-content-type
Dynamic: home-page
Dynamic: provides-extra
Dynamic: requires-dist
Dynamic: requires-python
Dynamic: summary
